sus_amongus/__init__.py
sus_amongus-0.69.dist-info/LICENSE
sus_amongus-0.69.dist-info/METADATA
sus_amongus-0.69.dist-info/WHEEL
sus_amongus-0.69.dist-info/top_level.txt
sus_amongus-0.69.dist-info/RECORD
