Metadata-Version: 2.1
Name: sus_amongus
Version: 0.69
Summary: useful for identifying sussy bakas ඞ
Author-email: unnamed7353 <unnamed7353@gmail.com>
Classifier: Programming Language :: Python :: 3
Classifier: License :: OSI Approved :: MIT License
Classifier: Operating System :: OS Independent
Requires-Python: >=3.8
License-File: LICENSE
